a_pandas_ex_fastsort/LICENSE
a_pandas_ex_fastsort/README.MD
a_pandas_ex_fastsort/__init__.py
a_pandas_ex_fastsort/requirements.txt
a_pandas_ex_fastsort/thirdparty.json
a_pandas_ex_fastsort-0.10.dist-info/LICENSE.rst
a_pandas_ex_fastsort-0.10.dist-info/METADATA
a_pandas_ex_fastsort-0.10.dist-info/WHEEL
a_pandas_ex_fastsort-0.10.dist-info/top_level.txt
a_pandas_ex_fastsort-0.10.dist-info/RECORD
